pyulysses/alarmistic/__init__.py
pyulysses/alarmistic/teams.py
pyulysses/configs/__init__.py
pyulysses/configs/env_loader.py
pyulysses/contracts/aug/example/test_aug_developers_processed.py
pyulysses/contracts/cross_check/example/test_example_cross_developers.py
pyulysses/contracts/raw/example/test_example_developers_raw_processed.py
pyulysses/contracts/rfn/example/test_example_rfn_developers_processed.py
pyulysses/contracts/sources/example/test_example_source_developers.py
pyulysses/functions/add_metadata.py
pyulysses/functions/calculate_execution_time.py
pyulysses/functions/create_duckdb_table.py
pyulysses/functions/dremio_client.py
pyulysses/functions/export_parquet_data.py
pyulysses/functions/query_executor.py
pyulysses/functions/upload_df_in_s3.py
pyulysses/functions/upload_file_s3.py
pyulysses/logger/logger_config.py
pyulysses/main.py
pyulysses/plugins/auth_middleware.py
pyulysses/plugins/cookie_middleware.py
pyulysses/plugins/s3.py
pyulysses/projects/example_project/runner_example_project.py
pyulysses/refresh_metadata/refresh_metadata.py
pyulysses/refresh_metadata/tables.py
pyulysses/runner_configs.py
pyulysses-0.1.1.dist-info/LICENSE
pyulysses-0.1.1.dist-info/METADATA
pyulysses-0.1.1.dist-info/WHEEL
pyulysses-0.1.1.dist-info/entry_points.txt
pyulysses-0.1.1.dist-info/RECORD
