Metadata-Version: 2.3
Name: pyulysses
Version: 0.1.1
Summary: Data processing project
Author: wallace-graca
Author-email: wallace.camargo@galp.com
Requires-Python: >=3.11
Classifier: Programming Language :: Python :: 3
Classifier: Programming Language :: Python :: 3.11
Classifier: Programming Language :: Python :: 3.12
Classifier: Programming Language :: Python :: 3.13
Requires-Dist: boto3 (>=1.40.1,<2.0.0)
Requires-Dist: duckdb (>=1.3.2,<2.0.0)
Requires-Dist: numpy (>=2.3.2,<3.0.0)
Requires-Dist: pandas (>=2.3.3,<3.0.0)
Requires-Dist: pre-commit (>=4.3.0,<5.0.0)
Requires-Dist: pyarrow (>=21.0.0,<22.0.0)
Requires-Dist: python-dotenv (>=1.1.1,<2.0.0)
Requires-Dist: requests (>=2.32.4,<3.0.0)
